MANIFEST.in
PYPI_VERSION
Readme.md
setup.cfg
setup.py
pi3dpf_ns/__init__.py
pi3dpf_ns/pi3dpf_common/__init__.py
pi3dpf_ns/pi3dpf_common/pf.functions.sh
pi3dpf_ns/pi3dpf_common/pf.functions.sh-orig
pi3dpf_ns/pi3dpf_common/pf_common.py
pi3dpf_ns/pi3dpf_common/fonts/NotoSans+Thai+Weather.ttf
pi3dpf_ns/pi3dpf_common/fonts/erikflowers.github.io_weather-font-icons.xlsx
pi3dpf_ns/pi3dpf_common/fonts/weathericons-regular-webfont.ttf
pi3dpf_ns_pi3dpf_common.egg-info/PKG-INFO
pi3dpf_ns_pi3dpf_common.egg-info/SOURCES.txt
pi3dpf_ns_pi3dpf_common.egg-info/dependency_links.txt
pi3dpf_ns_pi3dpf_common.egg-info/not-zip-safe
pi3dpf_ns_pi3dpf_common.egg-info/requires.txt
pi3dpf_ns_pi3dpf_common.egg-info/top_level.txt